LICENSE
MANIFEST.in
README.md
README.rst
pyproject.toml
requirements.txt
setup.cfg
setup.py
src/programming_with_pixels.egg-info/PKG-INFO
src/programming_with_pixels.egg-info/SOURCES.txt
src/programming_with_pixels.egg-info/dependency_links.txt
src/programming_with_pixels.egg-info/entry_points.txt
src/programming_with_pixels.egg-info/requires.txt
src/programming_with_pixels.egg-info/top_level.txt
src/pwp/__init__.py
src/pwp/cli.py
src/pwp/agents/__init__.py
src/pwp/agents/assisted_agent.py
src/pwp/agents/computer_use_agent.py
src/pwp/agents/computer_use_agent_categ1.py
src/pwp/bench/__init__.py
src/pwp/bench/benchmark.py
src/pwp/docker/Dockerfile
src/pwp/docker/fileview-0.0.1.vsix
src/pwp/docker/start.sh
src/pwp/docker/VSCode-linux-x64/LICENSES.chromium.html
src/pwp/docker/VSCode-linux-x64/chrome-sandbox
src/pwp/docker/VSCode-linux-x64/chrome_100_percent.pak
src/pwp/docker/VSCode-linux-x64/chrome_200_percent.pak
src/pwp/docker/VSCode-linux-x64/chrome_crashpad_handler
src/pwp/docker/VSCode-linux-x64/icudtl.dat
src/pwp/docker/VSCode-linux-x64/libEGL.so
src/pwp/docker/VSCode-linux-x64/libGLESv2.so
src/pwp/docker/VSCode-linux-x64/libffmpeg.so
src/pwp/docker/VSCode-linux-x64/libvk_swiftshader.so
src/pwp/docker/VSCode-linux-x64/libvulkan.so.1
src/pwp/docker/VSCode-linux-x64/resources.pak
src/pwp/docker/VSCode-linux-x64/snapshot_blob.bin
src/pwp/docker/VSCode-linux-x64/v8_context_snapshot.bin
src/pwp/docker/VSCode-linux-x64/vk_swiftshader_icd.json
src/pwp/docker/VSCode-linux-x64/bin/code-oss
src/pwp/docker/VSCode-linux-x64/locales/af.pak
src/pwp/docker/VSCode-linux-x64/locales/am.pak
src/pwp/docker/VSCode-linux-x64/locales/ar.pak
src/pwp/docker/VSCode-linux-x64/locales/bg.pak
src/pwp/docker/VSCode-linux-x64/locales/bn.pak
src/pwp/docker/VSCode-linux-x64/locales/ca.pak
src/pwp/docker/VSCode-linux-x64/locales/cs.pak
src/pwp/docker/VSCode-linux-x64/locales/da.pak
src/pwp/docker/VSCode-linux-x64/locales/de.pak
src/pwp/docker/VSCode-linux-x64/locales/el.pak
src/pwp/docker/VSCode-linux-x64/locales/en-GB.pak
src/pwp/docker/VSCode-linux-x64/locales/en-US.pak
src/pwp/docker/VSCode-linux-x64/locales/es-419.pak
src/pwp/docker/VSCode-linux-x64/locales/es.pak
src/pwp/docker/VSCode-linux-x64/locales/et.pak
src/pwp/docker/VSCode-linux-x64/locales/fa.pak
