Metadata-Version: 2.2
Name: programming-with-pixels
Version: 0.1.4
Summary: Programming with Pixels (PwP) - A framework for computer-use software engineering agents
Home-page: https://github.com/ProgrammingWithPixels/pwp
Author: PWP Team
Author-email: PWP Team <pranjal2041@gmail.com>
License: MIT
Project-URL: Homepage, https://github.com/ProgrammingWithPixels/pwp
Project-URL: Documentation, https://www.programmingwithpixels.com
Project-URL: Bug Tracker, https://github.com/ProgrammingWithPixels/pwp/issues
Project-URL: Source Code, https://github.com/ProgrammingWithPixels/pwp
Classifier: Programming Language :: Python :: 3
Classifier: Programming Language :: Python :: 3.6
Classifier: Programming Language :: Python :: 3.7
Classifier: Programming Language :: Python :: 3.8
Classifier: Programming Language :: Python :: 3.9
Classifier: License :: OSI Approved :: MIT License
Classifier: Operating System :: OS Independent
Classifier: Development Status :: 4 - Beta
Classifier: Intended Audience :: Developers
Classifier: Intended Audience :: Science/Research
Classifier: Topic :: Scientific/Engineering :: Artificial Intelligence
Classifier: Topic :: Software Development :: Libraries
Requires-Python: >=3.6
License-File: LICENSE
Requires-Dist: google-generativeai
Requires-Dist: docker
Requires-Dist: pillow
Requires-Dist: opencv-python
Requires-Dist: tqdm
Requires-Dist: numpy
Requires-Dist: pandas
Requires-Dist: matplotlib
Requires-Dist: requests
Requires-Dist: litellm
Requires-Dist: datasets
Requires-Dist: gdown
Requires-Dist: imagehash
Provides-Extra: gpu
Requires-Dist: torch>=1.9.0; extra == "gpu"
Requires-Dist: torchvision>=0.10.0; extra == "gpu"
Provides-Extra: dev
Requires-Dist: black; extra == "dev"
Requires-Dist: isort; extra == "dev"
Requires-Dist: pytest; extra == "dev"
Requires-Dist: pytest-cov; extra == "dev"
Requires-Dist: twine; extra == "dev"
Requires-Dist: build; extra == "dev"
Dynamic: author
Dynamic: home-page
Dynamic: requires-python
